baikalnlpy/__init__.py
baikalnlpy/_custom_dict.py
baikalnlpy/_custom_dict_client.py
baikalnlpy/_lang_service_client.py
baikalnlpy/_tagger.py
baikalnlpy-1.1.0.dist-info/LICENSE
baikalnlpy-1.1.0.dist-info/WHEEL
baikalnlpy-1.1.0.dist-info/METADATA
baikalnlpy-1.1.0.dist-info/RECORD
