Metadata-Version: 2.1
Name: baikalnlpy
Version: 1.1.0
Summary: The baikal nlp python client library
Home-page: https://baikal.ai/nlpdemo
License: BSD-3-Clause
Keywords: NLP,Korean,Deep Learning,POS tagger,baikal.ai
Author: Gihyun YUN
Author-email: gih2yun@baikal.ai
Requires-Python: >=3.6,<4.0
Classifier: Development Status :: 5 - Production/Stable
Classifier: Intended Audience :: Developers
Classifier: Intended Audience :: Education
Classifier: Intended Audience :: Information Technology
Classifier: Intended Audience :: Science/Research
Classifier: License :: OSI Approved :: BSD License
Classifier: Natural Language :: Korean
Classifier: Operating System :: MacOS
Classifier: Operating System :: Microsoft :: Windows
Classifier: Operating System :: OS Independent
Classifier: Operating System :: POSIX
Classifier: Operating System :: Unix
Classifier: Programming Language :: Python :: 3
Classifier: Programming Language :: Python :: 3.10
Classifier: Programming Language :: Python :: 3.6
Classifier: Programming Language :: Python :: 3.7
Classifier: Programming Language :: Python :: 3.8
Classifier: Programming Language :: Python :: 3.9
Classifier: Topic :: Scientific/Engineering
Classifier: Topic :: Scientific/Engineering :: Artificial Intelligence
Classifier: Topic :: Scientific/Engineering :: Information Analysis
Classifier: Topic :: Software Development
Classifier: Topic :: Software Development :: Libraries
Classifier: Typing :: Typed
Requires-Dist: baikalai-apis (>=0.9.1,<0.10.0)
Requires-Dist: googleapis-common-protos (>=1.56.0,<2.0.0)
Requires-Dist: grpcio (>=1.32.0,<2.0.0)
Requires-Dist: protobuf (>=3.19.4,<4.0.0)
Project-URL: Repository, https://github.com/baikalai/baikalnlpy
